fileshimstem/__init__.py
fileshimstem/__main__.py
fileshimstem-0.1.0.dist-info/entry_points.txt
fileshimstem-0.1.0.dist-info/WHEEL
fileshimstem-0.1.0.dist-info/METADATA
fileshimstem-0.1.0.dist-info/RECORD
