Metadata-Version: 2.1
Name: fileshimstem
Version: 0.1.0
Summary: fileshimstem - a terrible way to expose a filesystem over the network
Keywords: terrible
Author-email: James Hodgkinson <james@terminaloutcomes.com>
Classifier: License :: OSI Approved :: MIT License
Requires-Dist: fastapi
Requires-Dist: uvicorn[standard]
Requires-Dist: GitPython
Requires-Dist: pytest ; extra == "dev"
Requires-Dist: pylint ; extra == "dev"
Requires-Dist: mypy ; extra == "dev"
Requires-Dist: flit ; extra == "dev"
Project-URL: Home, https://github.com/yaleman/fileshimstem
Provides-Extra: dev
